LICENSE
LICENSE.txt
MANIFEST.in
README.md
cue.py
dev-requirements.txt
requirements.txt
setup.py
pycue.egg-info/PKG-INFO
pycue.egg-info/SOURCES.txt
pycue.egg-info/dependency_links.txt
pycue.egg-info/requires.txt
pycue.egg-info/top_level.txt
tests/data_bad.yml
tests/data_ok.yml
tests/schema.cue
tests/test_cue.py
tests/__pycache__/test_cue.cpython-312-pytest-8.1.1.pyc