Metadata-Version: 2.1
Name: pycue
Version: 0.1.3
Summary: Python wrapper for https://cuelang.org
Home-page: https://github.com/tebeka/cue
Author: Miki Tebeka
Author-email: miki@353solutions.com
License: MIT
Classifier: Development Status :: 3 - Alpha
Classifier: Intended Audience :: Developers
Classifier: Operating System :: POSIX :: Linux
Classifier: Operating System :: MacOS
Classifier: Programming Language :: Python :: 3.7
Classifier: Programming Language :: Python :: 3.8
Classifier: Programming Language :: Python
Classifier: Topic :: Software Development :: Libraries :: Python Modules
Classifier: Topic :: Software Development :: Libraries
License-File: LICENSE
License-File: LICENSE.txt
Requires-Dist: pyyaml~=6.0
